topsis/__init__.py
topsis/topsis.py
topsis_teena_102217049-1.0.2.dist-info/LICENSE.txt
topsis_teena_102217049-1.0.2.dist-info/METADATA
topsis_teena_102217049-1.0.2.dist-info/WHEEL
topsis_teena_102217049-1.0.2.dist-info/entry_points.txt
topsis_teena_102217049-1.0.2.dist-info/top_level.txt
topsis_teena_102217049-1.0.2.dist-info/RECORD
