Metadata-Version: 2.2
Name: topsis-teena-102217049
Version: 1.0.2
Summary: A Python package to calculate TOPSIS rankings
Home-page: https://github.com/yourusername/topsis-package
Author: Teena Sapra
Author-email: teena.sapra13@gmail.com
Classifier: Programming Language :: Python :: 3
Classifier: License :: OSI Approved :: MIT License
Classifier: Operating System :: OS Independent
Requires-Python: >=3.6
License-File: LICENSE.txt
Requires-Dist: numpy
Requires-Dist: pandas
Dynamic: author
Dynamic: author-email
Dynamic: classifier
Dynamic: description
Dynamic: description-content-type
Dynamic: home-page
Dynamic: requires-dist
Dynamic: requires-python
Dynamic: summary
